Conversion/__init__.py
Conversion/convert.py
MyProject101-1.0.dist-info/METADATA
MyProject101-1.0.dist-info/WHEEL
MyProject101-1.0.dist-info/license
MyProject101-1.0.dist-info/top_level.txt
MyProject101-1.0.dist-info/RECORD
